CHANGES.rst
clean_ioc/__init__.py
clean_ioc/bundles.py
clean_ioc/core.py
clean_ioc/factories.py
clean_ioc/functional_utils.py
clean_ioc/generic_utils.py
clean_ioc/list_reduction_filters.py
clean_ioc/node_filters.py
clean_ioc/py.typed
clean_ioc/registration_filters.py
clean_ioc/type_filters.py
clean_ioc/utils.py
clean_ioc/value_factories.py
clean_ioc/ext/fastapi/__init__.py
clean_ioc/ext/fastapi/core.py
clean_ioc/ext/fastapi/dependencies.py
clean_ioc/ext/fastapi/py.typed
clean_ioc-1.20.2.dist-info/METADATA
clean_ioc-1.20.2.dist-info/WHEEL
clean_ioc-1.20.2.dist-info/licenses/LICENSE
clean_ioc-1.20.2.dist-info/RECORD
