Metadata-Version: 2.4
Name: clean_ioc
Version: 1.20.2
Summary: An IOC Container for Python 3.10+
Project-URL: Homepage, https://peter-daly.github.io/clean_ioc/
Project-URL: Repository, https://github.com/peter-daly/clean_ioc
Project-URL: Documentation, https://peter-daly.github.io/clean_ioc/
Author: Peter Daly
License-Expression: MIT
License-File: LICENSE
Keywords: dependency,hints,injection,inversion of control,ioc,type,typing
Classifier: Development Status :: 5 - Production/Stable
Requires-Python: <4,>=3.10
Requires-Dist: the-utility-belt<0.4,>=0.3.0
Provides-Extra: fastapi
Requires-Dist: fastapi<0.102,>=0.101.0; extra == 'fastapi'
